mm_async/__init__.py
mm_async/client.py
mm_async/constants.py
mm_async/exceptions.py
mm_async/models.py
mm_async/py.typed
mm_async/retry.py
mm_async/api/__init__.py
mm_async/api/base.py
mm_async/api/channels.py
mm_async/api/posts.py
mm_async/api/teams.py
mm_async/api/users.py
mm_async-0.4.2.dist-info/METADATA
mm_async-0.4.2.dist-info/WHEEL
mm_async-0.4.2.dist-info/RECORD
