Metadata-Version: 2.4
Name: mm-async
Version: 0.4.2
Summary: Async HTTP client for Mattermost API
Author: Aleksei Anashkin
License-Expression: MIT
Requires-Python: >=3.11
Requires-Dist: httpx>=0.28.0
Requires-Dist: pydantic>=2.12.5
Provides-Extra: dev
Requires-Dist: mypy>=1.19.1; extra == 'dev'
Requires-Dist: pre-commit>=4.5.1; extra == 'dev'
Requires-Dist: pytest-asyncio>=1.3.0; extra == 'dev'
Requires-Dist: pytest-cov>=7.0.0; extra == 'dev'
Requires-Dist: pytest>=9.0.2; extra == 'dev'
Requires-Dist: ruff>=0.14.10; extra == 'dev'
